mud_examples/__init__.py
mud_examples/experiments.py
mud_examples/models.py
mud_examples/monomial.py
mud_examples/ode.py
mud_examples/parsers.py
mud_examples/pde.py
mud_examples/plotting.py
mud_examples/poisson.py
mud_examples/runner.py
mud_examples/summary.py
mud_examples/utils.py
mud_examples/data/pde_2D/ref_1000_2u.pkl
mud_examples/data/pde_2D/ref_950_2n.pkl
mud_examples/data/pde_2D/ref_990_2n.pkl
mud_examples/linear/__init__.py
mud_examples/linear/lin.py
mud_examples/linear/models.py
mud_examples-0.2.2.dist-info/AUTHORS.rst
mud_examples-0.2.2.dist-info/LICENSE.txt
mud_examples-0.2.2.dist-info/METADATA
mud_examples-0.2.2.dist-info/WHEEL
mud_examples-0.2.2.dist-info/entry_points.txt
mud_examples-0.2.2.dist-info/top_level.txt
mud_examples-0.2.2.dist-info/RECORD
