Metadata-Version: 2.1
Name: mud-examples
Version: 0.2.2
Summary: Maximal Updated Density Examples
Home-page: https://github.com/mathematicalmichael/mud-examples.git
Author: Mathematical Michael
Author-email: consistentbayes@gmail.com
License: mit
Project-URL: Documentation, https://github.com/mathematicalmichael/mud-examples.git
Platform: any
Classifier: Development Status :: 4 - Beta
Classifier: Programming Language :: Python
Requires-Python: >=3.5
Requires-Dist: mud !=0.1.0,>=0.0.24
Requires-Dist: numpy
Requires-Dist: scipy
Requires-Dist: matplotlib
Requires-Dist: importlib-metadata ; python_version < "3.10"
Provides-Extra: dev
Requires-Dist: pytest ; extra == 'dev'
Requires-Dist: pytest-cov ; extra == 'dev'
Requires-Dist: coverage ; extra == 'dev'
Requires-Dist: coveralls ; extra == 'dev'
Requires-Dist: flake8 ; extra == 'dev'
Requires-Dist: black ; extra == 'dev'
Requires-Dist: pre-commit ; extra == 'dev'
Provides-Extra: pub
Requires-Dist: setuptools ; extra == 'pub'
Requires-Dist: setuptools-scm ; extra == 'pub'
Requires-Dist: wheel ; extra == 'pub'
Requires-Dist: twine ; extra == 'pub'
